{
  "collectionName": "components_sections_forms",
  "info": {
    "displayName": "Form"
  },
  "options": {},
  "attributes": {
    "title": {
      "type": "string",
      "required": true
    },
    "submissionType": {
      "type": "enumeration",
      "required": true,
      "enum": [
        "SubmitOnce ",
        "AllowUpdate",
        "AllowMultiple"
      ]
    },
    "redirectTo": {
      "type": "string",
      "required": true
    },
    "field": {
      "type": "component",
      "component": "form.field",
      "repeatable": true
    },
    "formUniqueName": {
      "type": "string",
      "required": true,
      "unique": true
    },
    "firstName": {
      "type": "string"
    },
    "lastName": {
      "type": "string"
    },
    "email": {
      "type": "string",
      "required": true
    },
    "contactNumber": {
      "type": "string"
    }
  },
  "config": {}
}
